experimental/__init__.py
experimental/configs/projects/zephyr/README.md
experimental/configs/projects/zephyr/evaluation/eval.yaml
experimental/configs/projects/zephyr/sft/full_gcp_job.yaml
experimental/configs/projects/zephyr/sft/full_train.yaml
experimental/configs/projects/zephyr/sft/qlora_gcp_job.yaml
experimental/configs/projects/zephyr/sft/qlora_train.yaml
experimental/configs/recipes/phi3/dpo/fsdp_gcp_job.yaml
experimental/configs/recipes/phi3/dpo/fsdp_nvidia_24g_train.yaml
experimental/notebooks/Oumi - Datasets Tutorial.ipynb
oumi/__init__.py
oumi/__main__.py
oumi/evaluate.py
oumi/evaluate_async.py
oumi/infer.py
oumi/judge.py
oumi/synth.py
oumi/train.py
oumi/tune.py
oumi/builders/__init__.py
oumi/builders/callbacks.py
oumi/builders/collators.py
oumi/builders/data.py
oumi/builders/inference_engines.py
oumi/builders/lr_schedules.py
oumi/builders/metrics.py
oumi/builders/models.py
oumi/builders/optimizers.py
oumi/builders/oumi_data.py
oumi/builders/processors.py
oumi/builders/quantizers.py
oumi/builders/rewards.py
oumi/builders/rollouts.py
oumi/builders/training.py
oumi/builders/tuning.py
oumi/cli/__init__.py
oumi/cli/alias.py
oumi/cli/analyze.py
oumi/cli/cache.py
oumi/cli/cli_utils.py
oumi/cli/completions.py
oumi/cli/distributed_run.py
oumi/cli/env.py
oumi/cli/evaluate.py
oumi/cli/fetch.py
oumi/cli/infer.py
oumi/cli/judge.py
oumi/cli/launch.py
oumi/cli/main.py
oumi/cli/quantize.py
oumi/cli/synth.py
oumi/cli/train.py
oumi/cli/tune.py
oumi/core/__init__.py
oumi/core/async_utils.py
oumi/core/constants.py
oumi/core/distributed.py
oumi/core/analyze/__init__.py
oumi/core/analyze/column_types.py
oumi/core/analyze/dataframe_analyzer.py
oumi/core/analyze/dataset_analyzer.py
oumi/core/analyze/length_analyzer.py
oumi/core/analyze/sample_analyzer.py
oumi/core/callbacks/__init__.py
oumi/core/callbacks/base_trainer_callback.py
oumi/core/callbacks/bitnet_callback.py
oumi/core/callbacks/hf_mfu_callback.py
oumi/core/callbacks/metrics_logger_callback.py
oumi-0.7.dist-info/licenses/LICENSE
oumi-0.7.dist-info/METADATA
oumi-0.7.dist-info/WHEEL
oumi-0.7.dist-info/entry_points.txt
oumi-0.7.dist-info/top_level.txt
oumi-0.7.dist-info/RECORD
