Metadata-Version: 2.4
Name: oumi
Version: 0.7
Summary: Oumi - Modeling Platform
Author-email: Oumi Team <contact@oumi.ai>
License:                                  Apache License
Project-URL: Homepage, https://github.com/oumi-ai/oumi
Project-URL: Issues, https://github.com/oumi-ai/oumi/issues
Classifier: Programming Language :: Python :: 3
Classifier: Programming Language :: Python :: 3.10
Classifier: Programming Language :: Python :: 3.11
Classifier: Programming Language :: Python :: 3.12
Classifier: Programming Language :: Python :: 3.13
Classifier: Programming Language :: Python :: 3.14
Classifier: Operating System :: OS Independent
Classifier: Development Status :: 3 - Alpha
Classifier: Intended Audience :: Developers
Classifier: Topic :: Scientific/Engineering :: Artificial Intelligence
Requires-Python: <3.15,>=3.10
License-File: LICENSE
Requires-Dist: accelerate<2.0,>=1.10.0
Requires-Dist: aiohttp<3.16,>=3.12
Requires-Dist: aiofiles<26,>=24.1.0
Requires-Dist: aioresponses<0.8,>=0.7
Requires-Dist: backoff<2.3,>=2.2.1
Requires-Dist: click<8.4.0
Requires-Dist: datasets<5,>=3.2
Requires-Dist: greenlet
Requires-Dist: hdrhistogram<0.11,>=0.10
Requires-Dist: jsonlines
Requires-Dist: lm_eval[wandb]<0.5.0,>=0.4
Requires-Dist: mlflow>=3.1
Requires-Dist: numpy<2.4,>=1.26
Requires-Dist: omegaconf==2.4.0.dev4
Requires-Dist: packaging
Requires-Dist: pandas<3,>=2.3
Requires-Dist: peft<0.19,>=0.17
Requires-Dist: pexpect<4.10,>=4.9
Requires-Dist: posthog<8.0,>=7.0
Requires-Dist: pillow<12.2,>=11.3
Requires-Dist: protobuf>=6.32
Requires-Dist: pycares<6.0.0
Requires-Dist: pydantic<2.13,>=2.11
Requires-Dist: responses<0.26,>=0.25
Requires-Dist: safetensors<0.8,>=0.6
Requires-Dist: skypilot<0.11,>=0.10.2
Requires-Dist: tensorboard<2.21,>=2.20
Requires-Dist: torch<2.10.0,>=2.6
Requires-Dist: torchao<0.16,>=0.12
Requires-Dist: torchvision<0.25,>=0.21
Requires-Dist: tqdm
Requires-Dist: transformers<4.58,>=4.57
Requires-Dist: trl<0.27,>=0.24
Requires-Dist: typer<0.21.2
Requires-Dist: typing_extensions
Requires-Dist: uvicorn<0.41.0
Requires-Dist: wandb<0.25,>=0.21
Provides-Extra: dev
Requires-Dist: ipykernel; extra == "dev"
Requires-Dist: ipywidgets; extra == "dev"
Requires-Dist: jupyterlab; extra == "dev"
Requires-Dist: nbconvert; extra == "dev"
Requires-Dist: nbformat; extra == "dev"
Requires-Dist: pre-commit; extra == "dev"
Requires-Dist: pyright; extra == "dev"
Requires-Dist: pytest-asyncio; extra == "dev"
Requires-Dist: pytest-cov; extra == "dev"
Requires-Dist: pytest-timeout; extra == "dev"
Requires-Dist: pytest; extra == "dev"
Requires-Dist: responses; extra == "dev"
Requires-Dist: ruff; extra == "dev"
Requires-Dist: torchfix; extra == "dev"
Provides-Extra: docs
Requires-Dist: myst_parser; extra == "docs"
Requires-Dist: myst-nb; extra == "docs"
Requires-Dist: sphinx-book-theme; extra == "docs"
Requires-Dist: sphinx-copybutton; extra == "docs"
Requires-Dist: sphinx-design; extra == "docs"
Requires-Dist: sphinx; extra == "docs"
Requires-Dist: sphinxcontrib-bibtex; extra == "docs"
Requires-Dist: sphinxcontrib-mermaid; extra == "docs"
Requires-Dist: sphinxcontrib-typer; extra == "docs"
Provides-Extra: gpu
Requires-Dist: liger-kernel<0.7,>=0.6; extra == "gpu"
Requires-Dist: nvidia-ml-py<13.591,>=13.580; extra == "gpu"
Requires-Dist: bitsandbytes<0.50,>=0.47; extra == "gpu"
Requires-Dist: verl<0.6,>=0.5; python_version >= "3.10" and extra == "gpu"
Requires-Dist: vllm<0.11,>=0.10; extra == "gpu"
Provides-Extra: deepspeed
Requires-Dist: deepspeed<0.19.0,>=0.17.0; extra == "deepspeed"
Provides-Extra: aws
Requires-Dist: skypilot[aws]; extra == "aws"
Provides-Extra: azure
Requires-Dist: skypilot[azure]; extra == "azure"
Provides-Extra: gcp
Requires-Dist: google-api-core>=2.25; extra == "gcp"
Requires-Dist: google-api-python-client; extra == "gcp"
Requires-Dist: google-auth>=2.40; extra == "gcp"
Requires-Dist: google-cloud-core>=2.4; extra == "gcp"
Requires-Dist: google-cloud-storage>=3.3; extra == "gcp"
Requires-Dist: skypilot[gcp]; extra == "gcp"
Provides-Extra: kubernetes
Requires-Dist: skypilot[kubernetes]; extra == "kubernetes"
Provides-Extra: lambda
Requires-Dist: skypilot[lambda]; extra == "lambda"
Provides-Extra: runpod
Requires-Dist: skypilot[runpod]; extra == "runpod"
Provides-Extra: nebius
Requires-Dist: skypilot[nebius]; extra == "nebius"
Provides-Extra: synthesis
Requires-Dist: pdftext>=0.6.3; python_version >= "3.10" and extra == "synthesis"
Requires-Dist: python-docx>=1.1.0; extra == "synthesis"
Requires-Dist: openpyxl>=3.1.0; extra == "synthesis"
Provides-Extra: flash-attn
Requires-Dist: flash-attn>=2.0.0; extra == "flash-attn"
Provides-Extra: evaluation
Requires-Dist: alpaca-eval<0.7,>=0.6; python_version >= "3.10" and extra == "evaluation"
Requires-Dist: langdetect; extra == "evaluation"
Requires-Dist: immutabledict; extra == "evaluation"
Requires-Dist: nltk>=3.9; extra == "evaluation"
Requires-Dist: antlr4-python3-runtime==4.13.2; extra == "evaluation"
Requires-Dist: sympy>=1.14; extra == "evaluation"
Requires-Dist: sentencepiece>=0.2.0; extra == "evaluation"
Provides-Extra: quantization
Requires-Dist: autoawq<0.3,>=0.2; extra == "quantization"
Requires-Dist: bitsandbytes<0.50,>=0.47; extra == "quantization"
Provides-Extra: tune
Requires-Dist: optuna<5.0,>=4.0.0; extra == "tune"
Provides-Extra: bitnet
Requires-Dist: onebitllms>=0.0.3; extra == "bitnet"
Provides-Extra: file-formats
Requires-Dist: pdf2image<1.18,>=1.17; extra == "file-formats"
Requires-Dist: python-poppler<0.5,>=0.4; extra == "file-formats"
Provides-Extra: llama-cpp
Requires-Dist: llama-cpp-python<0.4,>=0.3.5; extra == "llama-cpp"
Provides-Extra: torchdata
Requires-Dist: torchdata<0.10.0,>=0.9; extra == "torchdata"
Provides-Extra: ci-cpu
Requires-Dist: oumi[dev,docs,gcp,synthesis,torchdata,tune]; extra == "ci-cpu"
Requires-Dist: vllm<0.11,>=0.10; extra == "ci-cpu"
Requires-Dist: llama-cpp-python<0.4,>=0.3; extra == "ci-cpu"
Provides-Extra: ci-gpu
Requires-Dist: oumi[deepspeed,dev,docs,gcp,gpu,synthesis,torchdata,tune]; extra == "ci-gpu"
Requires-Dist: alpaca-eval<0.7,>=0.6; python_version >= "3.10" and extra == "ci-gpu"
Dynamic: license-file
